buildkite_test_collector/__init__.py
buildkite_test_collector/collector/__init__.py
buildkite_test_collector/collector/api.py
buildkite_test_collector/collector/constants.py
buildkite_test_collector/collector/instant.py
buildkite_test_collector/collector/payload.py
buildkite_test_collector/collector/run_env.py
buildkite_test_collector/pytest_plugin/__init__.py
buildkite_test_collector/pytest_plugin/buildkite_plugin.py
buildkite_test_collector/pytest_plugin/failure_reasons.py
buildkite_test_collector/pytest_plugin/logger.py
buildkite_test_collector/pytest_plugin/span_collector.py
buildkite_test_collector-1.1.1.dist-info/METADATA
buildkite_test_collector-1.1.1.dist-info/WHEEL
buildkite_test_collector-1.1.1.dist-info/entry_points.txt
buildkite_test_collector-1.1.1.dist-info/licenses/LICENSE.txt
buildkite_test_collector-1.1.1.dist-info/RECORD
