Metadata-Version: 2.4
Name: buildkite-test-collector
Version: 1.1.1
Summary: Buildkite Test Engine collector
Project-URL: Homepage, https://github.com/buildkite/test-collector-python
Author-email: Buildkite <support@buildkite.com>
License-Expression: MIT
License-File: LICENSE.txt
Classifier: Framework :: Pytest
Classifier: License :: OSI Approved :: MIT License
Requires-Python: >=3.9
Requires-Dist: filelock>=3
Requires-Dist: pytest>=7
Requires-Dist: requests>=2
Provides-Extra: dev
Requires-Dist: check-manifest; extra == 'dev'
Requires-Dist: mock>=4; extra == 'dev'
Requires-Dist: pylint; extra == 'dev'
Requires-Dist: responses; extra == 'dev'
Requires-Dist: twine; extra == 'dev'
